Metadata-Version: 2.1
Name: devicepool
Version: 2.2.1
Summary: the package used to manage resources in the resource pool.
Home-page: https://github.com/dvdface/devicepool
Author: Ding Yi
Author-email: dvdface@hotmail.com
License: MIT
Platform: UNKNOWN
Classifier: Programming Language :: Python :: 3
Classifier: License :: OSI Approved :: MIT License
Classifier: Operating System :: OS Independent
Requires-Python: >=3.6
